hewwwo.py
hewwwo-1.0.6.dist-info/METADATA
hewwwo-1.0.6.dist-info/WHEEL
hewwwo-1.0.6.dist-info/top_level.txt
hewwwo-1.0.6.dist-info/RECORD
